{
  "_class": "shapeGroup",
  "clippingMaskMode": 0,
  "do_objectID": "3B6461EC-2D81-48E1-AF84-04B6754FEE4F",
  "exportOptions": {
    "_class": "exportOptions",
    "do_objectID": "D9AD1FE3-6968-47C0-B388-81C9849C8516",
    "exportFormats": [
    ],
    "includedLayerIds": [
    ],
    "layerOptions": 0,
    "shouldTrim": false
  },
  "frame": {
    "_class": "rect",
    "constrainProportions": false,
    "do_objectID": "911935C8-CD7F-4BAD-81FC-92772B3CC396",
    "height": 6,
    "width": 6,
    "x": 7,
    "y": 0
  },
  "hasClickThrough": false,
  "hasClippingMask": false,
  "isFlippedHorizontal": false,
  "isFlippedVertical": false,
  "isLocked": false,
  "isVisible": true,
  "layerListExpandedType": 0,
  "layers": [
    {
      "class": "oval",
      "id": "EC45834C-440A-44B2-9FFD-B000B4B5763A"
    }
  ],
  "name": "2",
  "nameIsFixed": false,
  "resizingConstraint": 63,
  "resizingType": 0,
  "rotation": 0,
  "shouldBreakMaskChain": false,
  "style": {
    "_class": "style",
    "do_objectID": "B31BB085-BA09-4B04-9620-41A724F55B19",
    "endDecorationType": 0,
    "fills": [
      {
        "_class": "fill",
        "color": {
          "_class": "color",
          "alpha": 1,
          "blue": 0,
          "green": 0,
          "red": 0
        },
        "fillType": 0,
        "isEnabled": true,
        "noiseIndex": 0,
        "noiseIntensity": 0,
        "patternFillType": 0,
        "patternTileScale": 1
      }
    ],
    "miterLimit": 10,
    "startDecorationType": 0
  },
  "userInfo": {
    "com.facebook.sketchplugins": {
      "FBLayerMetadata": {
        "FBSemaphore": {
          "objectID": "6775BAF5-1EA4-48B8-9F64-11AD0AE0ADEA"
        }
      }
    }
  },
  "windingRule": 1
}