{
  "_class": "group",
  "do_objectID": "09705319-6CBD-4B7A-968C-7924C6AB1034",
  "exportOptions": {
    "_class": "exportOptions",
    "exportFormats": [
    ],
    "includedLayerIds": [
    ],
    "layerOptions": 0,
    "shouldTrim": false
  },
  "frame": {
    "_class": "rect",
    "constrainProportions": false,
    "height": 72,
    "width": 375,
    "x": 0,
    "y": 0
  },
  "hasClickThrough": false,
  "isFlippedHorizontal": false,
  "isFlippedVertical": false,
  "isLocked": false,
  "isVisible": true,
  "layerListExpandedType": 2,
  "layers": [
    {
      "class": "shapeGroup",
      "id": "041D1E2B-F1C7-4515-84F8-1EEE7BC6C4B7"
    },
    {
      "class": "group",
      "id": "6E290799-2D9B-44AD-A1D4-CE34E43314D1"
    },
    {
      "class": "group",
      "id": "CC389C54-F87E-4FD5-A526-755D35A8309D"
    }
  ],
  "name": "TopBar",
  "nameIsFixed": true,
  "resizingConstraint": 63,
  "resizingType": 0,
  "rotation": 0,
  "shouldBreakMaskChain": false,
  "style": {
    "_class": "style",
    "endDecorationType": 0,
    "miterLimit": 10,
    "startDecorationType": 0
  }
}